factorslib/__init__.py
factorslib/factors.py
factorslib-3.0.dist-info/LICENCE.txt
factorslib-3.0.dist-info/METADATA
factorslib-3.0.dist-info/WHEEL
factorslib-3.0.dist-info/top_level.txt
factorslib-3.0.dist-info/RECORD
