Metadata-Version: 2.1
Name: factorslib
Version: 3.0
Summary: financial factors calculation
Home-page: https://github.com/wytxty/factorslib
Author: wytxty
Author-email: yvettewkkaa@gmail.com
License: MIT
License-File: LICENCE.txt
